odoo/addons/picking_edit_printed_status/README.rst
odoo/addons/picking_edit_printed_status/__init__.py
odoo/addons/picking_edit_printed_status/__manifest__.py
odoo/addons/picking_edit_printed_status/readme/CONTRIBUTORS.md
odoo/addons/picking_edit_printed_status/readme/DESCRIPTION.md
odoo/addons/picking_edit_printed_status/readme/USAGE.md
odoo/addons/picking_edit_printed_status/static/description/icon.png
odoo/addons/picking_edit_printed_status/static/description/index.html
odoo/addons/picking_edit_printed_status/views/stock_picking_views.xml
odoo_addon_picking_edit_printed_status-16.0.1.0.0.1.dist-info/METADATA
odoo_addon_picking_edit_printed_status-16.0.1.0.0.1.dist-info/WHEEL
odoo_addon_picking_edit_printed_status-16.0.1.0.0.1.dist-info/top_level.txt
odoo_addon_picking_edit_printed_status-16.0.1.0.0.1.dist-info/RECORD
